crimson/folder_sync/__init__.py
crimson/folder_sync/debug.py
crimson/folder_sync/docs.py
crimson/folder_sync/filter.py
crimson/folder_sync/logger.py
crimson/folder_sync/sync_handlers/bi_sync_handler.py
crimson/folder_sync/sync_handlers/editable_sync_handler.py
crimson/folder_sync/sync_handlers/sync_handler.py
crimson/folder_sync/syncer/__init__.py
crimson/folder_sync/syncer/base_syncer.py
crimson/folder_sync/syncer/editable_syncer.py
crimson_folder_sync-0.3.0.dist-info/LICENSE
crimson_folder_sync-0.3.0.dist-info/METADATA
crimson_folder_sync-0.3.0.dist-info/WHEEL
crimson_folder_sync-0.3.0.dist-info/top_level.txt
crimson_folder_sync-0.3.0.dist-info/RECORD
